tailscale/__init__.py
tailscale/exceptions.py
tailscale/models.py
tailscale/py.typed
tailscale/tailscale.py
tailscale-0.6.2.dist-info/LICENSE.md
tailscale-0.6.2.dist-info/METADATA
tailscale-0.6.2.dist-info/WHEEL
tailscale-0.6.2.dist-info/RECORD
