Metadata-Version: 2.3
Name: tailscale
Version: 0.6.2
Summary: Asynchronous client for the Tailscale API.
License: MIT
Keywords: tailscale,vpn,wireguard,api,async,client
Author: Franck Nijhof
Author-email: opensource@frenck.dev
Maintainer: Franck Nijhof
Maintainer-email: opensource@frenck.dev
Requires-Python: >=3.11,<4.0
Classifier: Development Status :: 5 - Production/Stable
Classifier: Framework :: AsyncIO
Classifier: Intended Audience :: Developers
Classifier: License :: OSI Approved :: MIT License
Classifier: Natural Language :: English
Classifier: Programming Language :: Python :: 3
Classifier: Programming Language :: Python :: 3.11
Classifier: Programming Language :: Python :: 3.12
Classifier: Programming Language :: Python :: 3.13
Classifier: Topic :: Software Development :: Libraries :: Python Modules
Requires-Dist: aiohttp (>=3.0.0)
Requires-Dist: mashumaro (>=3.10)
Requires-Dist: orjson (>=3.9.8)
Requires-Dist: yarl (>=1.6.0)
Project-URL: Bug Tracker, https://github.com/frenck/python-tailscale/issues
Project-URL: Changelog, https://github.com/frenck/python-tailscale/releases
Project-URL: Documentation, https://github.com/frenck/python-tailscale
Project-URL: Homepage, https://github.com/frenck/python-tailscale
Project-URL: Repository, https://github.com/frenck/python-tailscale
